{
  "192.168.0.1": {
    "ip": "192.168.0.1",
    "packets": 3,
    "bytes": 0,
    "upload_bps": 0.0,
    "download_bps": 0.0,
    "protocols": {
      "raw": "\n===================================================================\nProtocol Hierarchy Statistics\nFilter: \n\neth                                      frames:3 bytes:126\n  arp                                    frames:3 bytes:126\n===================================================================\n"
    },
    "conversations": [
      "================================================================================\nUDP Conversations\nFilter:<No Filter>\n                                                           |       <-      | |       ->      | |     Total     |    Relative    |   Duration   |\n                                                           | Frames  Bytes | | Frames  Bytes | | Frames  Bytes |      Start     |              |\n================================================================================\n================================================================================\nTCP Conversations\nFilter:<No Filter>\n                                                           |       <-      | |       ->      | |     Total     |    Relative    |   Duration   |\n                                                           | Frames  Bytes | | Frames  Bytes | | Frames  Bytes |      Start     |              |\n================================================================================\n"
    ],
    "http_requests": [],
    "tls_sni": []
  },
  "192.168.0.100": {
    "ip": "192.168.0.100",
    "packets": 0,
    "bytes": 0,
    "upload_bps": 0,
    "download_bps": 0,
    "protocols": {},
    "conversations": [],
    "http_requests": [],
    "tls_sni": []
  },
  "192.168.0.102": {
    "ip": "192.168.0.102",
    "packets": 0,
    "bytes": 0,
    "upload_bps": 0,
    "download_bps": 0,
    "protocols": {},
    "conversations": [],
    "http_requests": [],
    "tls_sni": []
  }
}